cliptitle/__init__.py
cliptitle/clip_title_enhancer.py
cliptitle/icon.ico
cliptitle-1.0.3.dist-info/LICENSE
cliptitle-1.0.3.dist-info/METADATA
cliptitle-1.0.3.dist-info/WHEEL
cliptitle-1.0.3.dist-info/entry_points.txt
cliptitle-1.0.3.dist-info/top_level.txt
cliptitle-1.0.3.dist-info/RECORD
