Metadata-Version: 2.1
Name: cliptitle
Version: 1.0.3
Summary: A clipboard monitor that adds titles to copied URLs
Home-page: https://github.com/cyysky/cliptitle-enhancer
Author: FMCV
Author-email: chong@fmcv.my
Classifier: Programming Language :: Python :: 3
Classifier: License :: OSI Approved :: MIT License
Classifier: Operating System :: Microsoft :: Windows
Requires-Python: >=3.6
License-File: LICENSE
Requires-Dist: pyperclip
Requires-Dist: requests
Requires-Dist: beautifulsoup4
Requires-Dist: plyer
Requires-Dist: infi.systray
